setup.py
peewee_fake_fixtures/__init__.py
peewee_fake_fixtures.egg-info/PKG-INFO
peewee_fake_fixtures.egg-info/SOURCES.txt
peewee_fake_fixtures.egg-info/dependency_links.txt
peewee_fake_fixtures.egg-info/requires.txt
peewee_fake_fixtures.egg-info/top_level.txt