Metadata-Version: 1.1
Name: peewee-fake-fixtures
Version: 0.2
Summary: A Python based fixture generator for peewee databases
Home-page: UNKNOWN
Author: Jorge Niedbalski R.
Author-email: jnr@pyrosome.org
License: BSD
Keywords: fixture generator fake fake-factory peewee fixtures
Platform: UNKNOWN
Classifier: Development Status :: 3 - Alpha
Classifier: Intended Audience :: Developers
Classifier: Operating System :: Unix 
